libsnark/alt_bn128.py
libsnark/__init__.py
libsnark/_alt_bn128.cpython-38-x86_64-linux-gnu.so
libsnark/setup-win32.py
python_libsnark.libs/libboost_iostreams-758e0eb7.so.1.53.0
python_libsnark.libs/libgmpxx-2c7d730e.so.4.6.1
python_libsnark.libs/libgmp-817999ae.so.10.4.1
python_libsnark.libs/libz-745e0a09.so.1.2.7
python_libsnark.libs/libbz2-a273e504.so.1.0.6
python_libsnark-0.3.3.dist-info/LICENSE
python_libsnark-0.3.3.dist-info/top_level.txt
python_libsnark-0.3.3.dist-info/WHEEL
python_libsnark-0.3.3.dist-info/METADATA
python_libsnark-0.3.3.dist-info/RECORD
