Metadata-Version: 1.0
Name: python-libsnark
Version: 0.3.3
Summary: Python bindings for a restricted subset of libsnark
Home-page: https://github.com/meilof/python-libsnark
Author: Meilof Veeningen
Author-email: meilof@gmail.com
License: MIT
Platform: UNKNOWN
